setup.py
pandora/__init__.py
pandora/connection.py
pandora/crypt.py
pandora/keys.py
pandora/pandora.py
python_pandora.egg-info/PKG-INFO
python_pandora.egg-info/SOURCES.txt
python_pandora.egg-info/dependency_links.txt
python_pandora.egg-info/top_level.txt